AlignSubs/AlignSubs.py
AlignSubs/__init__.py
AlignSubs/__main__.py
alignsubs-0.3.2.dist-info/METADATA
alignsubs-0.3.2.dist-info/WHEEL
alignsubs-0.3.2.dist-info/entry_points.txt
alignsubs-0.3.2.dist-info/top_level.txt
alignsubs-0.3.2.dist-info/RECORD
