Metadata-Version: 2.4
Name: AlignSubs
Version: 0.3.2
Summary: AlignSubs: Alignment Substitution Analyzer (for nucleotide and aminoacid substitutions)
Home-page: https://github.com/karagol-taner/Alignment-Substitution-Analyzer
Author: Taner Karagol
Author-email: taner.karagol@gmail.com
License: GPL-3.0
Keywords: Alignment,FASTA,Clustal,MSA
Requires-Dist: biopython
Dynamic: author
Dynamic: author-email
Dynamic: home-page
Dynamic: keywords
Dynamic: license
Dynamic: requires-dist
Dynamic: summary
